CHANGES.rst
LICENSE
MANIFEST.in
README.rst
setup.py
possible/__init__.py
possible.egg-info/PKG-INFO
possible.egg-info/SOURCES.txt
possible.egg-info/dependency_links.txt
possible.egg-info/requires.txt
possible.egg-info/top_level.txt